llama_index/tools/azure_code_interpreter/__init__.py
llama_index/tools/azure_code_interpreter/base.py
llama_index_tools_azure_code_interpreter-0.5.1.dist-info/METADATA
llama_index_tools_azure_code_interpreter-0.5.1.dist-info/WHEEL
llama_index_tools_azure_code_interpreter-0.5.1.dist-info/licenses/LICENSE
llama_index_tools_azure_code_interpreter-0.5.1.dist-info/RECORD
