Metadata-Version: 2.4
Name: llama-index-tools-azure-code-interpreter
Version: 0.5.1
Summary: llama-index tools azure dynamic sessions integration for code interpreter
Author-email: Your Name <you@example.com>
Maintainer: ajhofmann
License-Expression: MIT
License-File: LICENSE
Requires-Python: <4.0,>=3.9
Requires-Dist: azure-identity<2,>=1.16.0
Requires-Dist: llama-index-core<0.15,>=0.13.0
Requires-Dist: requests<3,>=2.31.0
